LICENSE
README.md
setup.cfg
setup.py
robert/__init__.py
robert/__main__.py
robert/aqme.py
robert/argument_parser.py
robert/curate.py
robert/evaluate.py
robert/generate.py
robert/generate_utils.py
robert/predict.py
robert/predict_utils.py
robert/report.py
robert/report_utils.py
robert/robert.py
robert/utils.py
robert/verify.py
robert.egg-info/PKG-INFO
robert.egg-info/SOURCES.txt
robert.egg-info/dependency_links.txt
robert.egg-info/requires.txt
robert.egg-info/top_level.txt
robert/icons/Robert_icon.png
robert/icons/Robert_logo.jpg
robert/icons/Robert_logo_transparent.png
robert/icons/info_icon.png
robert/icons/pdf_icon.png
robert/icons/play_icon.png
robert/icons/stop_icon.png
robert/model_params/ADAB_params.yaml
robert/model_params/GB_params.yaml
robert/model_params/GP_params.yaml
robert/model_params/MVL_params.yaml
robert/model_params/NN_params.yaml
robert/model_params/RF_params.yaml
robert/model_params/VR_params.yaml
robert/report/GENERATE.png
robert/report/Robert_icon.ico
robert/report/Robert_logo.jpg
robert/report/Robert_logo1.jpg
robert/report/abbrev.png
robert/report/adv_anal.png
robert/report/features.png
robert/report/generate.png
robert/report/outliers.png
robert/report/pred.png
robert/report/repro.png
robert/report/score.png
robert/report/score_0.jpg
robert/report/score_1.jpg
robert/report/score_10.jpg
robert/report/score_2.jpg
robert/report/score_3.jpg
robert/report/score_4.jpg
robert/report/score_5.jpg
robert/report/score_6.jpg
robert/report/score_7.jpg
robert/report/score_8.jpg
robert/report/score_9.jpg
robert/report/score_w_1_0.jpg
robert/report/score_w_1_1.jpg
robert/report/score_w_2_0.jpg
robert/report/score_w_2_1.jpg
robert/report/score_w_2_2.jpg
robert/report/score_w_3_0.jpg
robert/report/score_w_3_1.jpg
robert/report/score_w_3_2.jpg
robert/report/score_w_3_3.jpg
robert/report/transpa.png
robert/report/y_distrib.png
tests/test_1curate.py
tests/test_2generate.py
tests/test_3verify.py
tests/test_4predict.py
tests/test_5aqme_n_full.py