Metadata-Version: 2.1
Name: robert
Version: 2.0.2
Summary: Refiner and Optimizer of a Bunch of Existing Regression Tools
Home-page: https://github.com/jvalegre/robert
Download-URL: https://github.com/jvalegre/robert/archive/refs/tags/2.0.2.tar.gz
Author: Juan V. Alegre Requena, David Dalmau
Author-email: jv.alegre@csic.es
License: MIT
Keywords: workflows,machine learning,cheminformatics,data curation,prediction,automated
Classifier: Development Status :: 5 - Production/Stable
Classifier: Intended Audience :: Developers
Classifier: Topic :: Software Development :: Build Tools
Classifier: License :: OSI Approved :: MIT License
Classifier: Programming Language :: Python :: 3.7
Classifier: Programming Language :: Python :: 3.8
Classifier: Programming Language :: Python :: 3.9
Classifier: Programming Language :: Python :: 3.10
Classifier: Programming Language :: Python :: 3.11
Classifier: Programming Language :: Python :: 3.12
Requires-Python: >=3.10
License-File: LICENSE
Requires-Dist: PyYAML==6.0.2
Requires-Dist: matplotlib==3.10.0
Requires-Dist: pandas==2.2.3
Requires-Dist: numpy==1.26.4
Requires-Dist: progress==1.6
Requires-Dist: seaborn==0.13.2
Requires-Dist: scipy==1.15.0
Requires-Dist: scikit-learn==1.6.0
Requires-Dist: bayesian-optimization==3.0.0b1
Requires-Dist: numba==0.60.0
Requires-Dist: shap==0.46.0
Requires-Dist: weasyprint==63.1
Requires-Dist: PySide6
Requires-Dist: PyMuPDF
Requires-Dist: ansi2html
Requires-Dist: rdkit==2024.3.3
